jujube_pill/__init__.py
jujubes_pill/__init__.py
jujubes_pill-1.0.8.dist-info/METADATA
jujubes_pill-1.0.8.dist-info/RECORD
jujubes_pill-1.0.8.dist-info/WHEEL
jujubes_pill-1.0.8.dist-info/entry_points.txt
jujubes_pill-1.0.8.dist-info/top_level.txt
jujubes_pill-1.0.8.dist-info/zip-safe
utils/__init__.py
utils/utils.py
