Metadata-Version: 2.1
Name: jujubes-pill
Version: 1.0.8
Summary: TEST TEST
Home-page: https://zhuanlan.zhihu.com/p/26159930
Author: haoxiang
Author-email: haoxiangsnr@gmail.com
Maintainer: haoxiang
Maintainer-email: haoxiangsnr@gmail.com
License: MIT
Platform: all
Classifier: Development Status :: 4 - Beta
Classifier: Operating System :: OS Independent
Classifier: Intended Audience :: Developers
Classifier: License :: OSI Approved :: MIT License
Classifier: Programming Language :: Python
Classifier: Programming Language :: Python :: Implementation
Classifier: Programming Language :: Python :: 2
Classifier: Programming Language :: Python :: 2.7
Classifier: Programming Language :: Python :: 3
Classifier: Programming Language :: Python :: 3.4
Classifier: Programming Language :: Python :: 3.5
Classifier: Programming Language :: Python :: 3.6
Classifier: Topic :: Software Development :: Libraries
